dccsx/__init__.py
dccsx/dccsfb.py
dccsx/lan_change.py
dccsx/logo.py
dccsx-0.0.4.dist-info/LICENSE
dccsx-0.0.4.dist-info/METADATA
dccsx-0.0.4.dist-info/WHEEL
dccsx-0.0.4.dist-info/entry_points.txt
dccsx-0.0.4.dist-info/top_level.txt
dccsx-0.0.4.dist-info/RECORD
