Metadata-Version: 2.1
Name: dccsx
Version: 0.0.4
Summary: this module team dccs personal module for using shortcut python code
Home-page: https://github.com/Dccs-team/dccsx
Author: Md Saimun
Author-email: teamdccs@gmail.com
Classifier: Development Status :: 5 - Production/Stable
Classifier: Intended Audience :: Developers
Classifier: License :: OSI Approved :: MIT License
Classifier: Programming Language :: Python :: 3
Classifier: Programming Language :: Python :: 3.6
Classifier: Programming Language :: Python :: 3.7
Classifier: Programming Language :: Python :: 3.8
Classifier: Programming Language :: Python :: 3.9
Requires-Python: >=3.6
License-File: LICENSE
Requires-Dist: requests
Requires-Dist: bs4
